llama_index/llms/aibadgr/__init__.py
llama_index/llms/aibadgr/base.py
llama_index_llms_aibadgr-0.1.0.dist-info/METADATA
llama_index_llms_aibadgr-0.1.0.dist-info/WHEEL
llama_index_llms_aibadgr-0.1.0.dist-info/licenses/LICENSE
llama_index_llms_aibadgr-0.1.0.dist-info/RECORD
