Metadata-Version: 2.4
Name: llama-index-llms-aibadgr
Version: 0.1.0
Summary: llama-index llms aibadgr integration
Author-email: Your Name <you@example.com>
License-Expression: MIT
License-File: LICENSE
Requires-Python: <4.0,>=3.9
Requires-Dist: llama-index-core<0.15,>=0.13.0
Requires-Dist: llama-index-llms-openai-like<0.6,>=0.5.0
